{
    "4a1d517f-55f8-4e6b-8a41-6c8f8220973d": {
        "cover": "https://cdn.penguin.co.uk/dam-assets/books/9780241655702/9780241655702-jacket-large.jpg",
        "title": "Watership Down",
        "author": "Richard Adams",
        "genre": "Adventure",
        "year": "2022",
        "pages": "640",
        "summary": "Sandleford Warren is in danger. Hazel's younger brother Fiver is convinced that a great evil is about \nto befall the land, but no one will listen. And why would they when it is Spring and the grass is fat and succulent? \nSo together Hazel and Fiver and a few other brave rabbits secretly leave behind the safety and strictures of the warren \nand hop tentatively out into a vast and strange world.\nChased by their former friends, hunted by dogs and foxes, avoiding farms and other human threats, but making new friends, \nHazel and his fellow rabbits dream of a new life in the emerald embrace of Watership Down . . .",
        "_id": "4a1d517f-55f8-4e6b-8a41-6c8f8220973d"
    },
    "8f4720cb-4400-4dce-993a-d7d0891d2117": {
        "cover": "https://cdn.penguin.co.uk/dam-assets/books/9781405943505/9781405943505-jacket-large.jpg",
        "title": "Someone Else’s Shoes",
        "author": "Jojo Moyes",
        "genre": "Romance",
        "year": "2023",
        "pages": "432",
        "summary": "Meet Sam. Meet Nisha.\nTwo women living very different lives.\nBut when their paths cross, causing each a world of trouble - and finding some missing shoes is the \nonly way to solve it - they’re left with a choice every woman must face: to walk alone, or stand together . . .",
        "_id": "8f4720cb-4400-4dce-993a-d7d0891d2117"
    },
    "e4232a18-093a-4e56-b422-244e57ce04b8": {
        "cover": "https://cdn.penguin.co.uk/dam-assets/books/9780241430934/9780241430934-jacket-large.jpg",
        "title": "Jane Eyre ",
        "author": "Charlotte Bronte",
        "genre": "Classic",
        "year": "656",
        "pages": "2010",
        "summary": "One of the most widely-read and enjoyed of all Victorian novels, and one of the greatest tales of\n a woman's struggle for dignity and love in a hard time.\nOrphaned Jane Eyre endures an unhappy childhood, hated by her aunt and cousins and then sent to comfortless\n Lowood School. But life there improves and Jane stays on as a teacher, though she still longs for love and\n friendship. At Mr Rochester's house, where she goes to work as a governess, she hopes she might have found \nthem - until she learns the terrible secret of the attic.",
        "_id": "e4232a18-093a-4e56-b422-244e57ce04b8"
    },
    "247102f9-37d0-4783-8436-eaaf7678d2c3": {
        "cover": "https://cdn.penguin.co.uk/dam-assets/books/9780099582632/9780099582632-jacket-large.jpg",
        "title": "Oliver Twist",
        "author": "Charles Dickens",
        "genre": "Classic",
        "year": "2013",
        "pages": "736",
        "summary": "Meet the Artful Dodger, as roistering and swaggering a young gentleman as ever stood four \nfoot six. With him, you’ll run down the dirty backstreets of London to be entertained by the Respectable \nOld Gentleman and his brood of thieves and pickpockets. Fagin will bring you to ‘the trade’, and make \nsomething of you, something profitable.But there’s something about the young orphan Oliver that’s too \ngood for this dark and dangerous world – can he ever escape its clutches?",
        "_id": "247102f9-37d0-4783-8436-eaaf7678d2c3"
    }
}